htcopkmeans/__init__.py
htcopkmeans/cop_kmeans.py
htcopkmeans/run_ckm.py
htcopkmeans-1.5.dist-info/LICENSE
htcopkmeans-1.5.dist-info/METADATA
htcopkmeans-1.5.dist-info/WHEEL
htcopkmeans-1.5.dist-info/top_level.txt
htcopkmeans-1.5.dist-info/RECORD
