Metadata-Version: 2.1
Name: htcopkmeans
Version: 1.5
Summary: This is just a copy of the original repo https://github.com/Behrouz-Babaki/COP-Kmeans
Home-page: https://github.com/hongtaoh/COP-Kmeans
Author: Behrouz Babaki
Author-email: 
License: MIT
License-File: LICENSE
